ace_sklearn_crfsuite/__init__.py
ace_sklearn_crfsuite/_fileresource.py
ace_sklearn_crfsuite/estimator.py
ace_sklearn_crfsuite/metrics.py
ace_sklearn_crfsuite/scorers.py
ace_sklearn_crfsuite/trainer.py
ace_sklearn_crfsuite-0.4.0.dist-info/LICENSE
ace_sklearn_crfsuite-0.4.0.dist-info/METADATA
ace_sklearn_crfsuite-0.4.0.dist-info/WHEEL
ace_sklearn_crfsuite-0.4.0.dist-info/top_level.txt
ace_sklearn_crfsuite-0.4.0.dist-info/RECORD
