Metadata-Version: 2.1
Name: ace-sklearn-crfsuite
Version: 0.4.0
Summary: Fork of sklearn-crfsuite to provides interface simlar to modern scikit-learn
Author-email: Sébastien Mosser <mossers@mcmaster.ca>
License: MIT
Project-URL: Homepage, https://github.com/ace-design/ace-sklearn-crfsuite
Keywords: sklearn,crf,crfsuite,crf++
Classifier: Development Status :: 3 - Alpha
Classifier: License :: OSI Approved :: MIT License
Classifier: Intended Audience :: Developers
Classifier: Operating System :: OS Independent
Classifier: Programming Language :: Python
Classifier: Programming Language :: Python :: 3.10
Requires-Python: >=3.10
License-File: LICENSE
Requires-Dist: tqdm (>=4.64.0)
Requires-Dist: scikit-learn (>=1.1.1)
Requires-Dist: tabulate (>=0.8.9)
Requires-Dist: python-crfsuite (>=0.9.6)
Provides-Extra: dev
Requires-Dist: pytest (>=7.1.2) ; extra == 'dev'
Requires-Dist: coverage (>=6.4.1) ; extra == 'dev'
